pympljstyle/__init__.py
pympljstyle/base.py
pympljstyle/interface.py
pympljstyle/journals.py
pympljstyle/py.typed
pympljstyle/utils.py
pympljstyle-0.2.dist-info/LICENSE
pympljstyle-0.2.dist-info/METADATA
pympljstyle-0.2.dist-info/WHEEL
pympljstyle-0.2.dist-info/top_level.txt
pympljstyle-0.2.dist-info/RECORD
