Metadata-Version: 2.1
Name: pympljstyle
Version: 0.2
Summary: Apply journal styles and requirements to `matplotlib` figures
Author-email: Damien Mannion <damien@djmannion.net>
Project-URL: Documentation, https://github.com/djmannion/pympljstyle#readme
Project-URL: Issues, https://github.com/djmannion/pympljstyle/issues
Project-URL: Source, https://github.com/djmannion/pympljstyle
Classifier: Development Status :: 3 - Alpha
Classifier: License :: OSI Approved :: MIT License
Classifier: Programming Language :: Python :: 3.10
Classifier: Programming Language :: Python :: 3.11
Classifier: Programming Language :: Python :: 3.12
Requires-Python: >=3.10
License-File: LICENSE
Requires-Dist: matplotlib
Requires-Dist: pint
Provides-Extra: build
Requires-Dist: build ; extra == 'build'
Requires-Dist: twine ; extra == 'build'
Provides-Extra: dev
Requires-Dist: pytest ; extra == 'dev'
Requires-Dist: black ; extra == 'dev'
Requires-Dist: mypy ; extra == 'dev'
Requires-Dist: ruff ; extra == 'dev'
Provides-Extra: interactive
Requires-Dist: ipython ; extra == 'interactive'
Requires-Dist: pickleshare ; extra == 'interactive'
